<Stores>
  <storeCode>6kfz20</storeCode>
  <managerCode>p44eh7</managerCode>
  <address>
    <street>217 Havey Plaza</street>
    <city>Jacksonville</city>
    <state>FL</state>
    <zipcode>32225</zipcode>
    <country>US</country>
  </address>
</Stores>
<Stores>
  <storeCode>j17zt5</storeCode>
  <managerCode>p44eh7</managerCode>
  <address>
    <street>99 Fuller Junction</street>
    <city>Huntington</city>
    <state>WV</state>
    <zipcode>25716</zipcode>
    <country>US</country>
  </address>
</Stores>
<Stores>
  <storeCode>5uim79</storeCode>
  <managerCode>w34jg2</managerCode>
  <address>
    <street>28 Clemons Alley</street>
    <city>Portland</city>
    <state>OR</state>
    <zipcode>97286</zipcode>
    <country>US</country>
  </address>
</Stores>
<Stores>
  <storeCode>y22lq6</storeCode>
  <managerCode>w34jg2</managerCode>
  <address>
    <street>92 Michigan Crossing</street>
    <city>Milwaukee</city>
    <state>WI</state>
    <zipcode>53220</zipcode>
    <country>US</country>
  </address>
</Stores>
<Stores>
  <storeCode>0wtw56</storeCode>
  <managerCode>3ogc73</managerCode>
  <address>
    <street>435 Banding Trail</street>
    <city>Lubbock</city>
    <state>TX</state>
    <zipcode>79491</zipcode>
    <country>US</country>
  </address>
</Stores>
